micro_core/__init__.py
micro_core-0.0.1.dist-info/METADATA
micro_core-0.0.1.dist-info/WHEEL
micro_core-0.0.1.dist-info/entry_points.txt
micro_core-0.0.1.dist-info/top_level.txt
micro_core-0.0.1.dist-info/RECORD
