Metadata-Version: 2.1
Name: micro-core
Version: 0.0.1
Summary: UNKNOWN
Home-page: https://github.com/micro-org/
Author: limanman
License: Apache License, Version 2.0
Platform: UNKNOWN
Requires-Dist: typing (==3.7.4.3)
Requires-Dist: eventlet (==0.31.0)
